pyhgvsv/__init__.py
pyhgvsv/models.py
pyhgvsv/utils.py
pyhgvsv/variants.py
pyhgvsv-0.2.dist-info/LICENSE
pyhgvsv-0.2.dist-info/METADATA
pyhgvsv-0.2.dist-info/WHEEL
pyhgvsv-0.2.dist-info/top_level.txt
pyhgvsv-0.2.dist-info/RECORD
