Metadata-Version: 2.1
Name: pyhgvsv
Version: 0.2
Summary: HGVS variant name parsing and generation with SV (structural variant) support
Author-email: Parker Payne <parker.payne@bcm.edu>
Project-URL: Homepage, https://github.com/parkerpayne/hgvsv
Classifier: Programming Language :: Python :: 3
Classifier: License :: OSI Approved :: MIT License
Classifier: Operating System :: OS Independent
Requires-Python: >=2.6
License-File: LICENSE
